[
  {
    "type": "page_view",
    "data": {
      "sessionId": "fb9hlc",
      "country": "Unknown"
    },
    "timestamp": "2026-02-20T06:47:45.319Z"
  },
  {
    "type": "page_view",
    "data": {
      "sessionId": "fb9hlc",
      "country": "Unknown"
    },
    "timestamp": "2026-02-20T06:47:45.322Z"
  },
  {
    "type": "roast_complete",
    "data": {
      "sessionId": "fb9hlc",
      "persona": "bateman",
      "mode": "email"
    },
    "timestamp": "2026-02-20T06:50:23.900Z"
  },
  {
    "type": "page_view",
    "data": {
      "sessionId": "uo71ae",
      "country": "IN"
    },
    "timestamp": "2026-02-20T06:54:19.439Z"
  },
  {
    "type": "page_view",
    "data": {
      "sessionId": "uo71ae",
      "country": "Unknown"
    },
    "timestamp": "2026-02-20T06:54:19.792Z"
  },
  {
    "type": "roast_complete",
    "data": {
      "sessionId": "uo71ae",
      "persona": "arnab",
      "mode": "email"
    },
    "timestamp": "2026-02-20T06:58:39.414Z"
  },
  {
    "type": "page_view",
    "data": {
      "sessionId": "dhcokv",
      "country": "Unknown"
    },
    "timestamp": "2026-02-20T07:07:00.978Z"
  },
  {
    "type": "page_view",
    "data": {
      "sessionId": "dhcokv",
      "country": "Unknown"
    },
    "timestamp": "2026-02-20T07:07:01.159Z"
  },
  {
    "type": "page_view",
    "data": {
      "sessionId": "900hpo",
      "country": "IN"
    },
    "timestamp": "2026-02-20T07:11:21.573Z"
  },
  {
    "type": "page_view",
    "data": {
      "sessionId": "900hpo",
      "country": "Unknown"
    },
    "timestamp": "2026-02-20T07:11:21.576Z"
  }
]